README.rst
setup.py
sqlfunc.py
sqlfunc.egg-info/PKG-INFO
sqlfunc.egg-info/SOURCES.txt
sqlfunc.egg-info/dependency_links.txt
sqlfunc.egg-info/top_level.txt