Metadata-Version: 1.1
Name: sqlfunc
Version: 0.1
Summary: Clever stuff with SQL in __doc__
Home-page: https://github.com/digitalmensch/sqlfunc
Author: Tobias Ammann
Author-email: UNKNOWN
License: MIT
Download-URL: https://pypi.python.org/pypi/sqlitent
Keywords: sqlite,function
Platform: any
Classifier: Development Status :: 4 - Beta
Classifier: Intended Audience :: Developers
Classifier: License :: OSI Approved :: MIT License
Classifier: Operating System :: OS Independent
Classifier: Programming Language :: Python
Classifier: Programming Language :: Python :: 3.6
Classifier: Topic :: Database :: Front-Ends
